odoo/addons/website_apps_store/README.rst
odoo/addons/website_apps_store/__init__.py
odoo/addons/website_apps_store/__manifest__.py
odoo/addons/website_apps_store/controllers/__init__.py
odoo/addons/website_apps_store/controllers/main.py
odoo/addons/website_apps_store/demo/product_template_demo.xml
odoo/addons/website_apps_store/i18n/website_apps_store.pot
odoo/addons/website_apps_store/models/__init__.py
odoo/addons/website_apps_store/models/product.py
odoo/addons/website_apps_store/models/product_template.py
odoo/addons/website_apps_store/static/src/css/main.less
odoo/addons/website_apps_store/static/src/css/style.css
odoo/addons/website_apps_store/static/src/js/website_apps_store_tour.js
odoo/addons/website_apps_store/static/src/js/website_sale.js
odoo/addons/website_apps_store/tests/__init__.py
odoo/addons/website_apps_store/tests/test_tour_website_apps_store.py
odoo/addons/website_apps_store/tests/test_website_apps_store.py
odoo/addons/website_apps_store/views/assets.xml
odoo/addons/website_apps_store/views/templates.xml
odoo11_addon_website_apps_store-11.0.3.0.1.dist-info/METADATA
odoo11_addon_website_apps_store-11.0.3.0.1.dist-info/RECORD
odoo11_addon_website_apps_store-11.0.3.0.1.dist-info/WHEEL
odoo11_addon_website_apps_store-11.0.3.0.1.dist-info/top_level.txt
