Metadata-Version: 2.1
Name: odoo11-addon-website-apps-store
Version: 11.0.3.0.1
Summary: Website Apps Store
Home-page: https://github.com/OCA/apps-store
Author: Odoo Community Association (OCA), BizzAppDev
Author-email: support@odoo-community.org
License: AGPL-3
Platform: UNKNOWN
Classifier: Programming Language :: Python
Classifier: Framework :: Odoo
Classifier: License :: OSI Approved :: GNU Affero General Public License v3
Requires-Python: >=2.7, !=3.0.*, !=3.1.*, !=3.2.*, !=3.3.*, !=3.4.*
Requires-Dist: odoo11-addon-apps-download
Requires-Dist: odoo11-addon-apps-product-creator
Requires-Dist: odoo11-addon-website-form-recaptcha
Requires-Dist: odoo (<11.1dev,>=11.0a)
